yatwin/__init__.py
yatwin/cameras/BaseCamera.py
yatwin/cameras/BaseHackedYatwin.py
yatwin/cameras/__init__.py
yatwin/cameras/decorators.py
yatwin/cameras/utils.py
yatwin/decorators/__init__.py
yatwin/decorators/debuggers.py
yatwin/interfaces/__init__.py
yatwin/interfaces/ftp/__init__.py
yatwin/interfaces/ftp/constants.py
yatwin/interfaces/ftp/decorators.py
yatwin/interfaces/ftp/errors.py
yatwin/interfaces/ftp/ftp.py
yatwin/interfaces/http/__init__.py
yatwin/interfaces/http/constants.py
yatwin/interfaces/http/http.py
yatwin/interfaces/http/response.py
yatwin/interfaces/http/utils.py
yatwin/interfaces/http/files/__init__.py
yatwin/interfaces/http/files/firmware_files.py
yatwin/interfaces/http/files/file_types/BaseFile.py
yatwin/interfaces/http/files/file_types/File.py
yatwin/interfaces/http/files/file_types/FirmwareFile.py
yatwin/interfaces/http/files/file_types/__init__.py
yatwin/interfaces/http/methods/__init__.py
yatwin/interfaces/http/methods/audiostream.py
yatwin/interfaces/http/methods/camera_control.py
yatwin/interfaces/http/methods/decoder_control.py
yatwin/interfaces/http/methods/del_file.py
yatwin/interfaces/http/methods/ftptest.py
yatwin/interfaces/http/methods/get_aging.py
yatwin/interfaces/http/methods/get_alarmlog.py
yatwin/interfaces/http/methods/get_apwifi.py
yatwin/interfaces/http/methods/get_camera_params.py
yatwin/interfaces/http/methods/get_factory_extra.py
yatwin/interfaces/http/methods/get_factory_param.py
yatwin/interfaces/http/methods/get_log.py
yatwin/interfaces/http/methods/get_misc.py
yatwin/interfaces/http/methods/get_onvif.py
yatwin/interfaces/http/methods/get_params.py
yatwin/interfaces/http/methods/get_pnp_server.py
yatwin/interfaces/http/methods/get_record.py
yatwin/interfaces/http/methods/get_record_file.py
yatwin/interfaces/http/methods/get_rtsp.py
yatwin/interfaces/http/methods/get_status.py
yatwin/interfaces/http/methods/get_wifi_scan_result.py
yatwin/interfaces/http/methods/livestream.py
yatwin/interfaces/http/methods/login.py
yatwin-0.0.1.dist-info/METADATA
yatwin-0.0.1.dist-info/WHEEL
yatwin-0.0.1.dist-info/top_level.txt
yatwin-0.0.1.dist-info/RECORD
