Metadata-Version: 2.1
Name: yatwin
Version: 0.0.1
Summary: Python 3 API for Yatwin and Vstarcam IP Cameras (Windows)
Home-page: https://github.com/tombulled/python-yatwin
Author: UNKNOWN
Author-email: UNKNOWN
License: UNKNOWN
Platform: UNKNOWN
Classifier: Programming Language :: Python :: 3
